napari_phasors/__init__.py
napari_phasors/_reader.py
napari_phasors/_sample_data.py
napari_phasors/_synthetic_generator.py
napari_phasors/_utils.py
napari_phasors/_version.py
napari_phasors/_widget.py
napari_phasors/_writer.py
napari_phasors/calibration_tab.py
napari_phasors/components_tab.py
napari_phasors/filter_tab.py
napari_phasors/fret_tab.py
napari_phasors/lifetime_tab.py
napari_phasors/napari.yaml
napari_phasors/plotter.py
napari_phasors/selection_tab.py
napari_phasors/_tests/__init__.py
napari_phasors/_tests/conftest.py
napari_phasors/_tests/test_calibration_tab.py
napari_phasors/_tests/test_components_tab.py
napari_phasors/_tests/test_data_utils.py
napari_phasors/_tests/test_filter_tab.py
napari_phasors/_tests/test_fret_tab.py
napari_phasors/_tests/test_import_export_settings.py
napari_phasors/_tests/test_lifetime_tab.py
napari_phasors/_tests/test_plotter.py
napari_phasors/_tests/test_reader.py
napari_phasors/_tests/test_sample_data.py
napari_phasors/_tests/test_selection_tab.py
napari_phasors/_tests/test_synthetic_generator.py
napari_phasors/_tests/test_utils.py
napari_phasors/_tests/test_widget.py
napari_phasors/_tests/test_writer.py
napari_phasors/ui/calibration_widget.ui
napari_phasors/ui/plotter_inputs_widget.ui
napari_phasors/ui/selection_tab.ui
napari_phasors-0.3.0.dist-info/licenses/LICENSE
napari_phasors-0.3.0.dist-info/METADATA
napari_phasors-0.3.0.dist-info/WHEEL
napari_phasors-0.3.0.dist-info/entry_points.txt
napari_phasors-0.3.0.dist-info/top_level.txt
napari_phasors-0.3.0.dist-info/RECORD
