Metadata-Version: 2.4
Name: napari-phasors
Version: 0.3.0
Summary: A simple plugin to use phasor analysis
Author-email: Bruno Pannunzio <bpannunzio@pasteur.edu.uy>, Marcelo Leomil Zoccoler <marzoccoler@gmail.com>, Bruno Schuty <schutyb@schutyb.com>, Leonel Malacrida <lmalacrida@pasteur.edu.uy>
License: 
Project-URL: Homepage, https://github.com/napari-phasors/napari-phasors
Project-URL: Bug Tracker, https://github.com/napari-phasors/napari-phasors/issues
Project-URL: Documentation, https://github.com/napari-phasors/napari-phasors#README.md
Project-URL: Source Code, https://github.com/napari-phasors/napari-phasors
Project-URL: User Support, https://github.com/napari-phasors/napari-phasors/issues
Classifier: Development Status :: 2 - Pre-Alpha
Classifier: Framework :: napari
Classifier: Intended Audience :: Developers
Classifier: License :: OSI Approved :: BSD License
Classifier: Operating System :: OS Independent
Classifier: Programming Language :: Python
Classifier: Programming Language :: Python :: 3
Classifier: Programming Language :: Python :: 3 :: Only
Classifier: Programming Language :: Python :: 3.12
Classifier: Programming Language :: Python :: 3.13
Classifier: Topic :: Scientific/Engineering :: Image Processing
Classifier: Topic :: Scientific/Engineering :: Visualization
Requires-Python: >=3.12
License-File: LICENSE
Requires-Dist: phasorpy>=0.8
Requires-Dist: qtpy
Requires-Dist: scikit-image
Requires-Dist: biaplotter>=0.4.2
Requires-Dist: fbdfile
Requires-Dist: sdtfile
Requires-Dist: ptufile
Requires-Dist: tifffile
Requires-Dist: pandas
Requires-Dist: pyqt5
Requires-Dist: pawflim
Provides-Extra: testing
Requires-Dist: tox; extra == "testing"
Requires-Dist: pytest; extra == "testing"
Requires-Dist: pytest-cov; extra == "testing"
Requires-Dist: pytest-qt; extra == "testing"
Requires-Dist: napari; extra == "testing"
Requires-Dist: qtpy; extra == "testing"
Requires-Dist: scikit-image; extra == "testing"
Requires-Dist: biaplotter>=0.4.2; extra == "testing"
Requires-Dist: PyQt5; extra == "testing"
Requires-Dist: pandas; extra == "testing"
Requires-Dist: black; extra == "testing"
Requires-Dist: isort; extra == "testing"
Requires-Dist: phasorpy>=0.8; extra == "testing"
Requires-Dist: tifffile; extra == "testing"
Requires-Dist: fbdfile; extra == "testing"
Requires-Dist: sdtfile; extra == "testing"
Requires-Dist: ptufile; extra == "testing"
Requires-Dist: pawflim; extra == "testing"
Dynamic: license-file
